{"chunk_definitions":[{"row":27,"row_count":1,"visible":true,"expansion_state":0,"options":{"engine":"r","label":"unnamed-chunk-86","dev":"png"},"document_id":"33C0F960","chunk_id":"cm55kfqzhrz43","chunk_label":"unnamed-chunk-1"},{"row":39,"row_count":1,"visible":true,"expansion_state":0,"options":{"engine":"r","label":"unnamed-chunk-87","dev":"png"},"document_id":"33C0F960","chunk_id":"c75inouocgh2c","chunk_label":"unnamed-chunk-2"},{"row":76,"row_count":1,"visible":true,"expansion_state":0,"options":{"engine":"r","label":"unnamed-chunk-88","dev":"png"},"document_id":"33C0F960","chunk_id":"cb641rph5n8ka","chunk_label":"unnamed-chunk-3"},{"row":88,"row_count":1,"visible":true,"expansion_state":0,"options":{"engine":"r","label":"unnamed-chunk-89","dev":"png"},"document_id":"33C0F960","chunk_id":"c9jxi7qmyh4xn","chunk_label":"unnamed-chunk-4"},{"row":112,"row_count":1,"visible":true,"expansion_state":0,"options":{"engine":"r","label":"unnamed-chunk-90","dev":"png"},"document_id":"33C0F960","chunk_id":"c4n3ppj9dekri","chunk_label":"unnamed-chunk-5"},{"row":119,"row_count":1,"visible":true,"expansion_state":0,"options":{"engine":"r","label":"unnamed-chunk-91","dev":"png"},"document_id":"33C0F960","chunk_id":"cczh1ehomce5d","chunk_label":"unnamed-chunk-6"},{"row":152,"row_count":1,"visible":true,"expansion_state":0,"options":{"engine":"r","label":"unnamed-chunk-92","dev":"png"},"document_id":"33C0F960","chunk_id":"cj4z1rfy7izpp","chunk_label":"unnamed-chunk-7"},{"row":184,"row_count":1,"visible":true,"expansion_state":0,"options":{"engine":"r","label":"unnamed-chunk-93","dev":"png"},"document_id":"33C0F960","chunk_id":"cj9vxo35zn2d7","chunk_label":"unnamed-chunk-8"},{"row":217,"row_count":1,"visible":true,"expansion_state":0,"options":{"engine":"r","label":"unnamed-chunk-94","dev":"png"},"document_id":"33C0F960","chunk_id":"cyyn81ty1kavy","chunk_label":"unnamed-chunk-9"},{"row":227,"row_count":1,"visible":true,"expansion_state":0,"options":{"engine":"r","label":"unnamed-chunk-95","dev":"png"},"document_id":"33C0F960","chunk_id":"cbqhhtrlx2oc7","chunk_label":"unnamed-chunk-10"},{"row":240,"row_count":1,"visible":true,"expansion_state":0,"options":{"engine":"r","label":"unnamed-chunk-96","dev":"png"},"document_id":"33C0F960","chunk_id":"crwj1956o8u2d","chunk_label":"unnamed-chunk-11"},{"row":252,"row_count":1,"visible":true,"expansion_state":0,"options":{"engine":"r","label":"unnamed-chunk-97","dev":"png"},"document_id":"33C0F960","chunk_id":"c6pa197eqam6i","chunk_label":"unnamed-chunk-12"},{"row":264,"row_count":1,"visible":true,"expansion_state":0,"options":{"engine":"r","label":"unnamed-chunk-98","dev":"png"},"document_id":"33C0F960","chunk_id":"curvynayg8338","chunk_label":"unnamed-chunk-13"},{"row":273,"row_count":1,"visible":true,"expansion_state":0,"options":{"engine":"r","label":"unnamed-chunk-99","dev":"png"},"document_id":"33C0F960","chunk_id":"cwlleqszsbcd1","chunk_label":"unnamed-chunk-14"},{"row":283,"row_count":1,"visible":true,"expansion_state":0,"options":{"engine":"r","label":"unnamed-chunk-100","dev":"png"},"document_id":"33C0F960","chunk_id":"czmednrvo0v38","chunk_label":"unnamed-chunk-15"},{"row":306,"row_count":1,"visible":true,"expansion_state":0,"options":{"engine":"r","label":"unnamed-chunk-101","dev":"png"},"document_id":"33C0F960","chunk_id":"cmnltt6cumqch","chunk_label":"unnamed-chunk-16"},{"row":325,"row_count":1,"visible":true,"expansion_state":0,"options":{"engine":"r","label":"unnamed-chunk-102","dev":"png"},"document_id":"33C0F960","chunk_id":"chog8aok99iwo","chunk_label":"unnamed-chunk-17"},{"row":347,"row_count":1,"visible":true,"expansion_state":0,"options":{"engine":"r","label":"unnamed-chunk-103","dev":"png"},"document_id":"33C0F960","chunk_id":"cq7hmwlsr2lkg","chunk_label":"unnamed-chunk-18"},{"row":397,"row_count":1,"visible":true,"expansion_state":0,"options":{"engine":"r","label":"unnamed-chunk-104","dev":"png"},"document_id":"33C0F960","chunk_id":"clsj6gqqnmv2e","chunk_label":"unnamed-chunk-19"},{"row":421,"row_count":1,"visible":true,"expansion_state":0,"options":{"engine":"r","label":"unnamed-chunk-105","dev":"png"},"document_id":"33C0F960","chunk_id":"ctraehg8gd3dd","chunk_label":"unnamed-chunk-20"},{"row":465,"row_count":1,"visible":true,"expansion_state":0,"options":{"engine":"r","label":"unnamed-chunk-106","dev":"png"},"document_id":"33C0F960","chunk_id":"c2402o1m1p2z9","chunk_label":"unnamed-chunk-21"},{"row":488,"row_count":1,"visible":true,"expansion_state":0,"options":{"engine":"r","label":"unnamed-chunk-107","dev":"png"},"document_id":"33C0F960","chunk_id":"cy0u71mj0bdt6","chunk_label":"unnamed-chunk-22"}],"doc_write_time":1754959987,"chunk_rendered_width":700}